muse/__init__.py
muse/__main__.py
muse/carbon_budget.py
muse/commodities.py
muse/conftest.py
muse/constraints.py
muse/costs.py
muse/decisions.py
muse/defaults.py
muse/demand_matching.py
muse/demand_share.py
muse/errors.py
muse/examples.py
muse/filters.py
muse/hooks.py
muse/interactions.py
muse/investments.py
muse/lp_adapter.py
muse/mca.py
muse/objectives.py
muse/production.py
muse/quantities.py
muse/registration.py
muse/regressions.py
muse/timeslices.py
muse/utilities.py
muse/wizard.py
muse/agents/__init__.py
muse/agents/agent.py
muse/agents/factories.py
muse/data/README.md
muse/data/default_settings.toml
muse/data/example/default/Agents.csv
muse/data/example/default/GlobalCommodities.csv
muse/data/example/default/Projections.csv
muse/data/example/default/settings.toml
muse/data/example/default/gas/CommIn.csv
muse/data/example/default/gas/CommOut.csv
muse/data/example/default/gas/ExistingCapacity.csv
muse/data/example/default/gas/Technodata.csv
muse/data/example/default/power/CommIn.csv
muse/data/example/default/power/CommOut.csv
muse/data/example/default/power/ExistingCapacity.csv
muse/data/example/default/power/Technodata.csv
muse/data/example/default/residential/CommIn.csv
muse/data/example/default/residential/CommOut.csv
muse/data/example/default/residential/ExistingCapacity.csv
muse/data/example/default/residential/Technodata.csv
muse/data/example/default/residential_presets/Residential2020Consumption.csv
muse/data/example/default/residential_presets/Residential2050Consumption.csv
muse/data/example/default_correlation/Macrodrivers.csv
muse/data/example/default_correlation/TimesliceSharepreset.csv
muse/data/example/default_correlation/regressionparameters.csv
muse/data/example/default_retro/Agents.csv
muse/data/example/default_retro/GlobalCommodities.csv
muse/data/example/default_retro/Projections.csv
muse/data/example/default_retro/settings.toml
muse/data/example/default_retro/gas/CommIn.csv
muse/data/example/default_retro/gas/CommOut.csv
muse_os-1.5.4.dist-info/licenses/LICENSE
muse_os-1.5.4.dist-info/METADATA
muse_os-1.5.4.dist-info/WHEEL
muse_os-1.5.4.dist-info/entry_points.txt
muse_os-1.5.4.dist-info/top_level.txt
muse_os-1.5.4.dist-info/RECORD
