Metadata-Version: 2.4
Name: MUSE_OS
Version: 1.5.4
Summary: Energy System Model
Author-email: "Hawkes Research Group @ Chemical Engineering, Imperial College London" <a.hawkes@imperial.ac.uk>, Imperial College London RSE Team <ict-rse-team@imperial.ac.uk>
License:                     GNU GENERAL PUBLIC LICENSE
Project-URL: Homepage, https://www.imperial.ac.uk/muse-energy/what-is-muse-/
Keywords: energy,modelling
Classifier: Development Status :: 4 - Beta
Classifier: Programming Language :: Python :: 3.9
Classifier: Programming Language :: Python :: 3.10
Classifier: Programming Language :: Python :: 3.11
Classifier: Programming Language :: Python :: 3.12
Classifier: Programming Language :: Python :: 3.13
Classifier: Intended Audience :: Science/Research
Classifier: Intended Audience :: Other Audience
Classifier: License :: OSI Approved :: GNU General Public License v3 (GPLv3)
Requires-Python: <3.14,>=3.9
License-File: LICENSE
Requires-Dist: numpy>=2.0
Requires-Dist: scipy>=1.13
Requires-Dist: pandas>=2.2
Requires-Dist: xarray<=2024.11,>=2024.6
Requires-Dist: bottleneck>=1.4
Requires-Dist: coloredlogs
Requires-Dist: toml
Requires-Dist: xlrd
Requires-Dist: mypy-extensions
Requires-Dist: pypubsub
Requires-Dist: tomlkit
Provides-Extra: all
Requires-Dist: MUSE_OS[dev,doc,excel]; extra == "all"
Provides-Extra: dev
Requires-Dist: pytest>4.0.2; extra == "dev"
Requires-Dist: IPython; extra == "dev"
Requires-Dist: jupyter; extra == "dev"
Requires-Dist: nbconvert; extra == "dev"
Requires-Dist: nbformat; extra == "dev"
Requires-Dist: mypy; extra == "dev"
Requires-Dist: pytest-xdist; extra == "dev"
Requires-Dist: pyinstaller; extra == "dev"
Requires-Dist: pre-commit; extra == "dev"
Provides-Extra: doc
Requires-Dist: sphinx; extra == "doc"
Requires-Dist: sphinx-rtd-theme; extra == "doc"
Requires-Dist: ipykernel; extra == "doc"
Requires-Dist: nbsphinx; extra == "doc"
Requires-Dist: myst-parser; extra == "doc"
Requires-Dist: sphinxcontrib-bibtex; extra == "doc"
Requires-Dist: ipython; extra == "doc"
Requires-Dist: pandoc; extra == "doc"
Requires-Dist: seaborn; extra == "doc"
Provides-Extra: excel
Requires-Dist: openpyxl; extra == "excel"
Provides-Extra: gui
Requires-Dist: gooey; extra == "gui"
Dynamic: license-file
